zope/hookable/__init__.py
zope/hookable/_zope_hookable.c
zope/hookable/_zope_hookable.cpython-314-aarch64-linux-gnu.so
zope/hookable/tests/__init__.py
zope/hookable/tests/test_compile_flags.py
zope/hookable/tests/test_hookable.py
zope_hookable-8.2.dist-info/METADATA
zope_hookable-8.2.dist-info/WHEEL
zope_hookable-8.2.dist-info/top_level.txt
zope_hookable-8.2.dist-info/RECORD
zope_hookable-8.2.dist-info/licenses/LICENSE.txt
