Metadata-Version: 2.4
Name: zope.hookable
Version: 8.2
Summary: Zope hookable
Author-email: Zope Foundation and contributors <zope-dev@zope.dev>
Maintainer-email: Plone Foundation and contributors <zope-dev@zope.dev>
License-Expression: ZPL-2.1
Project-URL: Documentation, https://zopehookable.readthedocs.io
Project-URL: Issues, https://github.com/zopefoundation/zope.hookable/issues
Project-URL: Source, https://github.com/zopefoundation/zope.hookable
Project-URL: Changelog, https://github.com/zopefoundation/zope.hookable/blob/master/CHANGES.rst
Keywords: zope,function,hook,replacement,loose,coupled
Classifier: Development Status :: 5 - Production/Stable
Classifier: Framework :: Zope :: 3
Classifier: Intended Audience :: Developers
Classifier: Operating System :: OS Independent
Classifier: Programming Language :: Python
Classifier: Programming Language :: Python :: 3
Classifier: Programming Language :: Python :: 3 :: Only
Classifier: Programming Language :: Python :: 3.10
Classifier: Programming Language :: Python :: 3.11
Classifier: Programming Language :: Python :: 3.12
Classifier: Programming Language :: Python :: 3.13
Classifier: Programming Language :: Python :: 3.14
Classifier: Programming Language :: Python :: Implementation :: CPython
Classifier: Programming Language :: Python :: Implementation :: PyPy
Requires-Python: >=3.10
License-File: LICENSE.txt
Provides-Extra: docs
Requires-Dist: Sphinx; extra == "docs"
Requires-Dist: furo; extra == "docs"
Provides-Extra: test
Requires-Dist: zope.testing; extra == "test"
Requires-Dist: zope.testrunner>=6.4; extra == "test"
Provides-Extra: testing
Requires-Dist: coverage; extra == "testing"
Requires-Dist: zope.testing; extra == "testing"
Requires-Dist: zope.testrunner>=6.4; extra == "testing"
Dynamic: license-file
